LICENSE.txt
setup.py
SecuCrypt.egg-info/PKG-INFO
SecuCrypt.egg-info/SOURCES.txt
SecuCrypt.egg-info/dependency_links.txt
SecuCrypt.egg-info/top_level.txt
SecuCrypttract/SecuCrypt.py
SecuCrypttract/__init__.py